mlgear/__init__.py
mlgear/aggregators.py
mlgear/cv.py
mlgear/encoders.py
mlgear/lr_scheduler.py
mlgear/metrics.py
mlgear/models.py
mlgear/tracker.py
mlgear/utils.py
mlgear-0.5.dist-info/LICENSE.txt
mlgear-0.5.dist-info/METADATA
mlgear-0.5.dist-info/WHEEL
mlgear-0.5.dist-info/RECORD
