Metadata-Version: 2.3
Name: mlgear
Version: 0.5
Summary: Utility scripts for machine learning
License: MIT
Author: Peter Hurford
Author-email: peter@peterhurford.com
Requires-Python: >=3.7,<4.0
Classifier: Development Status :: 3 - Alpha
Classifier: License :: OSI Approved :: MIT License
Classifier: Operating System :: OS Independent
Classifier: Programming Language :: Python :: 3
Classifier: Programming Language :: Python :: 3.7
Classifier: Programming Language :: Python :: 3.8
Classifier: Programming Language :: Python :: 3.9
Classifier: Programming Language :: Python :: 3.10
Classifier: Programming Language :: Python :: 3.11
Classifier: Programming Language :: Python :: 3.12
Classifier: Programming Language :: Python :: 3.13
Requires-Dist: keras
Requires-Dist: lightgbm
Requires-Dist: numpy
Requires-Dist: pandas
Requires-Dist: scikit-learn
Project-URL: Repository, https://github.com/peterhurford/mlgear
